i_airtable/__init__.py
i_airtable/connector.py
i_airtable-0.2.1.dist-info/LICENSE
i_airtable-0.2.1.dist-info/METADATA
i_airtable-0.2.1.dist-info/WHEEL
i_airtable-0.2.1.dist-info/RECORD
