Metadata-Version: 2.3
Name: i-airtable
Version: 0.2.1
Summary: Airtable connector for the Aracnid integration framework
License: MIT
Keywords: connector
Author: Jason Romano
Author-email: aracnid@gmail.com
Requires-Python: >=3.10,<4.0
Classifier: License :: OSI Approved :: MIT License
Classifier: Programming Language :: Python :: 3
Classifier: Programming Language :: Python :: 3.10
Classifier: Programming Language :: Python :: 3.11
Classifier: Programming Language :: Python :: 3.12
Classifier: Programming Language :: Python :: 3.13
Requires-Dist: aracnid-core (>=0.1.3,<0.2.0)
Requires-Dist: pyairtable (>=3.1.1,<4.0.0)
Project-URL: Repository, https://github.com/aracnid/i-airtable
